sqlalchemy3/__init__.py
sqlalchemy3/connectors/__init__.py
sqlalchemy3/connectors/aioodbc.py
sqlalchemy3/connectors/asyncio.py
sqlalchemy3/connectors/pyodbc.py
sqlalchemy3/crud.py
sqlalchemy3/dialects/__init__.py
sqlalchemy3/dialects/_typing.py
sqlalchemy3/dialects/mssql/__init__.py
sqlalchemy3/dialects/mssql/aioodbc.py
sqlalchemy3/dialects/mssql/base.py
sqlalchemy3/dialects/mssql/information_schema.py
sqlalchemy3/dialects/mssql/json.py
sqlalchemy3/dialects/mssql/provision.py
sqlalchemy3/dialects/mssql/pymssql.py
sqlalchemy3/dialects/mssql/pyodbc.py
sqlalchemy3/dialects/mysql/__init__.py
sqlalchemy3/dialects/mysql/aiomysql.py
sqlalchemy3/dialects/mysql/asyncmy.py
sqlalchemy3/dialects/mysql/base.py
sqlalchemy3/dialects/mysql/cymysql.py
sqlalchemy3/dialects/mysql/dml.py
sqlalchemy3/dialects/mysql/enumerated.py
sqlalchemy3/dialects/mysql/expression.py
sqlalchemy3/dialects/mysql/json.py
sqlalchemy3/dialects/mysql/mariadb.py
sqlalchemy3/dialects/mysql/mariadbconnector.py
sqlalchemy3/dialects/mysql/mysqlconnector.py
sqlalchemy3/dialects/mysql/mysqldb.py
sqlalchemy3/dialects/mysql/provision.py
sqlalchemy3/dialects/mysql/pymysql.py
sqlalchemy3/dialects/mysql/pyodbc.py
sqlalchemy3/dialects/mysql/reflection.py
sqlalchemy3/dialects/mysql/reserved_words.py
sqlalchemy3/dialects/mysql/types.py
sqlalchemy3/dialects/oracle/__init__.py
sqlalchemy3/dialects/oracle/base.py
sqlalchemy3/dialects/oracle/cx_oracle.py
sqlalchemy3/dialects/oracle/dictionary.py
sqlalchemy3/dialects/oracle/oracledb.py
sqlalchemy3/dialects/oracle/provision.py
sqlalchemy3/dialects/oracle/types.py
sqlalchemy3/dialects/postgresql/__init__.py
sqlalchemy3/dialects/postgresql/_psycopg_common.py
sqlalchemy3/dialects/postgresql/array.py
sqlalchemy3/dialects/postgresql/asyncpg.py
sqlalchemy3/dialects/postgresql/base.py
sqlalchemy3/dialects/postgresql/dml.py
sqlalchemy3/dialects/postgresql/ext.py
sqlalchemy3/dialects/postgresql/hstore.py
sqlalchemy3/dialects/postgresql/json.py
sqlalchemy3-0.1.3.dist-info/METADATA
sqlalchemy3-0.1.3.dist-info/WHEEL
sqlalchemy3-0.1.3.dist-info/RECORD
