Metadata-Version: 2.1
Name: sqlalchemy3
Version: 0.1.3
Summary: Python操作数据库的ORM框架
Author: zhangdapeng
Author-email: 1156956636@qq.com
Requires-Python: >=3.8,<4.0
Classifier: Programming Language :: Python :: 3
Classifier: Programming Language :: Python :: 3.8
Classifier: Programming Language :: Python :: 3.9
Classifier: Programming Language :: Python :: 3.10
Classifier: Programming Language :: Python :: 3.11
Classifier: Programming Language :: Python :: 3.12
Classifier: Programming Language :: Python :: 3.13
Requires-Dist: aiomysql (>=0.2.0,<0.3.0)
Requires-Dist: aiosqlite (>=0.20.0,<0.21.0)
Requires-Dist: asyncpg (>=0.30.0,<0.31.0)
